AUTHORS.rst
CONTRIBUTING.rst
HISTORY.rst
LICENSE
MANIFEST.in
README.rst
setup.cfg
setup.py
dbaas_laas/__init__.py
dbaas_laas/laas_client.py
dbaas_laas/provider.py
dbaas_laas.egg-info/PKG-INFO
dbaas_laas.egg-info/SOURCES.txt
dbaas_laas.egg-info/dependency_links.txt
dbaas_laas.egg-info/not-zip-safe
dbaas_laas.egg-info/top_level.txt
docs/Makefile
docs/authors.rst
docs/conf.py
docs/contributing.rst
docs/history.rst
docs/index.rst
docs/installation.rst
docs/make.bat
docs/readme.rst
docs/usage.rst
tests/__init__.py
tests/test_dbaas-laas.py