Metadata-Version: 1.1
Name: dbaas-laas
Version: 0.0.4
Summary: Python dbaas laas template
Home-page: https://github.com/ricardosdias/dbaas-laas
Author: Ricardo Dias
Author-email: ricardo@ricardodias.org
License: BSD
Keywords: dbaas-laas
Platform: UNKNOWN
Classifier: Development Status :: 2 - Pre-Alpha
Classifier: Intended Audience :: Developers
Classifier: License :: OSI Approved :: BSD License
Classifier: Natural Language :: English
Classifier: Programming Language :: Python :: 2
Classifier: Programming Language :: Python :: 2.6
Classifier: Programming Language :: Python :: 2.7
Classifier: Programming Language :: Python :: 3
Classifier: Programming Language :: Python :: 3.3
Classifier: Programming Language :: Python :: 3.4
